{
  "transactions": [
    {
      "id": 1,
      "name": "Salary from Google",
      "type": "income",
      "amount": 1000000
    },
    {
      "id": 2,
      "name": "Family Expenses",
      "type": "expense",
      "amount": 200000
    },
    {
      "id": 4,
      "name": "PizzaBurg",
      "amount": "200",
      "type": "income"
    },
    {
      "id": 5,
      "name": "Found2",
      "amount": 22,
      "type": "expense"
    },
    {
      "name": "Mobile",
      "amount": 300000,
      "type": "expense",
      "id": 6
    }
  ]
}